bits/__init__.py
bits/pathable/__init__.py
bits/pathable/sso.py
bits_pathable-1.0.2.dist-info/METADATA
bits_pathable-1.0.2.dist-info/WHEEL
bits_pathable-1.0.2.dist-info/top_level.txt
bits_pathable-1.0.2.dist-info/RECORD
