Metadata-Version: 2.1
Name: bits-pathable
Version: 1.0.2
Summary: BITS Pathable
Home-page: UNKNOWN
Author: Lukas Karlsson
Author-email: karlsson@broadinstitute.org
License: Apache Software License
Platform: UNKNOWN
